daft_property_price_register/__init__.py
daft_property_price_register/constants.py
daft_property_price_register/logging.py
daft_property_price_register/utils.py
daft_property_price_register/bin/__init__.py
daft_property_price_register/bin/load.py
daft_property_price_register/bin/scrape.py
daft_property_price_register/models/__init__.py
daft_property_price_register/models/daft_sale.py
daft_property_price_register/resources/DAFT.csv.tar.gz
daft_property_price_register-0.0.2.dist-info/LICENSE
daft_property_price_register-0.0.2.dist-info/METADATA
daft_property_price_register-0.0.2.dist-info/WHEEL
daft_property_price_register-0.0.2.dist-info/entry_points.txt
daft_property_price_register-0.0.2.dist-info/top_level.txt
daft_property_price_register-0.0.2.dist-info/RECORD
