Metadata-Version: 2.1
Name: daft-property-price-register
Version: 0.0.2
Summary: UNKNOWN
Home-page: https://github.com/RobertLucey/daft-property-price-register
Author: Robert Lucey
License: UNKNOWN
Platform: UNKNOWN
Requires-Python: >=3.5
License-File: LICENSE
Requires-Dist: requests
Requires-Dist: cached-property
Requires-Dist: requests-ip-rotator
Requires-Dist: bs4
Requires-Dist: pandas
